django_public_project-0.7.5.dist-info/DESCRIPTION.rst
django_public_project-0.7.5.dist-info/METADATA
django_public_project-0.7.5.dist-info/metadata.json
django_public_project-0.7.5.dist-info/RECORD
django_public_project-0.7.5.dist-info/top_level.txt
django_public_project-0.7.5.dist-info/WHEEL
example_project/create_example_data.sh
example_project/init_example_project.sh
example_project/manage.py
example_project/runserver.sh
example_project/ep_setup_app/__init__.py
example_project/ep_setup_app/example_data.py
example_project/ep_setup_app/models.py
example_project/ep_setup_app/tests.py
example_project/ep_setup_app/views.py
example_project/ep_setup_app/docs/dofston_cert_refusal.pdf
example_project/ep_setup_app/docs/phonecall_mrs_smith.pdf
example_project/ep_setup_app/imgs/Bruegel_Tower_of_Babel_1.jpg
example_project/ep_setup_app/management/__init__.py
example_project/ep_setup_app/management/commands/__init__.py
example_project/ep_setup_app/management/commands/createexampledata.py
example_project/example_project/__init__.py
example_project/example_project/settings.py
example_project/example_project/urls.py
example_project/example_project/wsgi.py
public_project/__init__.py
public_project/admin.py
public_project/api.py
public_project/context_processors.py
public_project/doc_scanner.py
public_project/feeds.py
public_project/forms.py
public_project/models.py
public_project/search.py
public_project/tag_cache_creator.py
public_project/tests.py
public_project/urls.py
public_project/views.py
public_project/locale/de/LC_MESSAGES/django.mo
public_project/locale/de/LC_MESSAGES/django.po
public_project/locale/en/LC_MESSAGES/django.mo
public_project/locale/en/LC_MESSAGES/django.po
public_project/management/__init__.py
public_project/management/commands/__init__.py
public_project/management/commands/createpages.py
public_project/management/commands/generatepdfimages.py
public_project/management/commands/rebuildsearchtagcache.py
public_project/migrations/0001_initial.py
public_project/migrations/0002_boolean_default_values.py
public_project/migrations/0003_removed_null_on_manytomany.py
public_project/migrations/0004_activation_flags_for_goals_questions_comments.py
public_project/migrations/__init__.py
