Metadata-Version: 2.0
Name: django-public-project
Version: 0.7.5
Summary: Custom CMS for making public projects, political processes or enquiry commission work more transparent
Home-page: https://github.com/holgerd77/django-public-project
Author: Holger Drewes
Author-email: Holger.Drewes@gmail.com
License: UNKNOWN
Platform: UNKNOWN
Classifier: Development Status :: 4 - Beta
Classifier: Environment :: Web Environment
Classifier: Framework :: Django
Classifier: Intended Audience :: Developers
Classifier: License :: OSI Approved :: BSD License
Classifier: Operating System :: OS Independent
Classifier: Programming Language :: Python
Classifier: Topic :: Scientific/Engineering :: Information Analysis
Requires-Dist: Django (>=1.10,<1.11)
Requires-Dist: pdfminer (==20110515)
Requires-Dist: Pillow
Requires-Dist: django-tastypie (>=0.13.3,<1.0)
